mstools/__init__.py
mstools/mstools.py
mstools-0.1.0.dist-info/LICENSE
mstools-0.1.0.dist-info/WHEEL
mstools-0.1.0.dist-info/METADATA
mstools-0.1.0.dist-info/RECORD
