Metadata-Version: 2.1
Name: mstools
Version: 0.1.0
Summary: Top-level package for mstools package.
Home-page: https://github.com/eamontoyaa/mstools
License: UNKNOWN
Author: Exneyder A. Montoya-Araque
Author-email: eamontoyaa@gmail.com
Requires-Python: >=3.6
Classifier: Intended Audience :: Developers
Classifier: License :: OSI Approved :: BSD License
Classifier: Programming Language :: Python :: 3
Classifier: Topic :: Software Development :: Libraries :: Python Modules
Requires-Dist: numpy >= 1.19.1
Project-URL: Documentation, https://mstools.readthedocs.io
